lipsum_easydataframe/__init__.py
lipsum_easydataframe/dataframe_helper.py
lipsum_easydataframe/dataframe_in.py
easydataframe_lipsum-0.0.3.dist-info/LICENSE
easydataframe_lipsum-0.0.3.dist-info/METADATA
easydataframe_lipsum-0.0.3.dist-info/WHEEL
easydataframe_lipsum-0.0.3.dist-info/top_level.txt
easydataframe_lipsum-0.0.3.dist-info/RECORD
