Metadata-Version: 2.1
Name: easydataframe-lipsum
Version: 0.0.3
Summary: A library that handles small xlsx files as a DataFrame.
Home-page: https://gitlab.com/NilPointer/easydataframe
Author: lipsum
License: UNKNOWN
Platform: UNKNOWN
Classifier: Development Status :: 3 - Alpha
Classifier: Programming Language :: Python :: 3.8
Classifier: License :: OSI Approved :: BSD License
Classifier: Operating System :: Microsoft :: Windows :: Windows 10
Requires-Python: >=3.8
Requires-Dist: pandas
Requires-Dist: openpyxl
